{
    "company_name": "Marhaba Hotel",
    "phone_number": "+923193417373",
    "reviews": [
        {
            "review_id": "ChZDSUhNMG9nS0VOLW5xdGFBNkl2OEN3EAE",
            "reviewer": "Adeela Ayub",
            "rating": "No rating",
            "review_text": "I'm impressed by the hotel's economical rates and top-notch service. The rooms are clean and cozy, and the location is perfect for exploring the city. Highly recommend for anyone looking for a great deal.",
            "date": ""
        },
        {
            "review_id": "Ci9DQUlRQUNvZENodHljRjlvT21rMlRtOUVibGt5VjB4VmJuVkZZbE5xVHpOQ1RWRRAB",
            "reviewer": "Bilal Akbar",
            "rating": "No rating",
            "review_text": "Hotel marhaba is a very luxury and very happy and very peaceful staff all the staff is very good ac working 24 hour working and very child services ac and am stay in 8 to10 days you are come to marhaba hotel and happy your holidays ❤️",
            "date": ""
        },
        {
            "review_id": "ChdDSUhNMG9nS0VLcnI2UFNKNmVLNTRRRRAB",
            "reviewer": "Nazim bro",
            "rating": "1.0",
            "review_text": "Now I'm from sialkot but i stay in tha marhaba hotel but hear very poor service AC room only allow 3 hourse AC. Washroom 🤢😷smail and not water for fresh. Marhaba Hotel not a good place for rest or sleep. Hear rent is very high.",
            "date": ""
        },
        {
            "review_id": "Ci9DQUlRQUNvZENodHljRjlvT2xoT2JFUjJjMFIyY3pReFVGRk1Xa3BDYkc1SU4xRRAB",
            "reviewer": "Shazil Ghazanfar",
            "rating": "No rating",
            "review_text": "Very nice hotel for families and bachelor's very polite staff , very clean hotel, I must recommend to everyone to visit onces",
            "date": ""
        },
        {
            "review_id": "ChdDSUhNMG9nS0VMcndvZWlwcFBIb2pnRRAB",
            "reviewer": "Trip.com Member",
            "rating": "No rating",
            "review_text": "They charge extra for AC rooms. They cut power also by themselves to save electricity. Rude staff. I would never recommend this hotel. Earlier view is fake. Terrible place to live",
            "date": ""
        },
        {
            "review_id": "ChZDSUhNMG9nS0VJVDIxN0R1bzVHaWNBEAE",
            "reviewer": "Trip.com Member",
            "rating": "No rating",
            "review_text": "Was a pleasant stay - good was great and outstanding cleanliness services. Public transport and amenities weren't too far either. Main location",
            "date": ""
        },
        {
            "review_id": "ChdDSUhNMG9nS0VPamk3ODJWak9yTjBBRRAB",
            "reviewer": "tasleem fazli",
            "rating": "No rating",
            "review_text": "This is very very best hotel of Rawalpindi\nTheir hospitality is very good management very best\nRooms are very luxurious vd suitable charges.i would like to prefer this hotel to all of my colleagues..\nRegards",
            "date": ""
        },
        {
            "review_id": "Ci9DQUlRQUNvZENodHljRjlvT21SblFYTmxXV1ZyZWpJeFpEWkNMVzlCV2xkU2RVRRAB",
            "reviewer": "Waqas Abbasi",
            "rating": "No rating",
            "review_text": "marhaba hotel exilant hotel the room r verry good hotel manghmet is verry best room sarvie verry good staff is verry good family hotel",
            "date": ""
        },
        {
            "review_id": "Ci9DQUlRQUNvZENodHljRjlvT21wYVpHRmZWVGcyUzE4elMzbERZVmxzYW5KM1VHYxAB",
            "reviewer": "Raja Sajid Munir",
            "rating": "No rating",
            "review_text": "The food is very good. All guests are invited to eat the food at this hotel.",
            "date": ""
        },
        {
            "review_id": "Ci9DQUlRQUNvZENodHljRjlvT2pkeE5HWnFSWG8xV2xReFYxVlhhbTAzTlVFMGMwRRAB",
            "reviewer": "Ayaz Khan",
            "rating": "No rating",
            "review_text": "Verry nice hotel verry good location",
            "date": ""
        },
        {
            "review_id": "ChZDSUhNMG9nS0VLNmhpdmZ0NTVxUVBBEAE",
            "reviewer": "Raja Ali",
            "rating": "No rating",
            "review_text": "Very nice hotel nice rooms  good sarvis. And safe location",
            "date": ""
        },
        {
            "review_id": "ChdDSUhNMG9nS0VMYmg3Yl9sOGREUXVBRRAB",
            "reviewer": "shahzad ahmed",
            "rating": "No rating",
            "review_text": "Very nice hotel.room are very good and also staff is very Good",
            "date": ""
        },
        {
            "review_id": "Ci9DQUlRQUNvZENodHljRjlvT2xOcGIzUkpRM1pyWm5aSldrVmxTbmxyV1VreFExRRAB",
            "reviewer": "Assad Ullah",
            "rating": "No rating",
            "review_text": "Nice hotel near and clean room",
            "date": ""
        },
        {
            "review_id": "ChdDSUhNMG9nS0VJQ0FnSURXOGFEbHBRRRAB",
            "reviewer": "Tahir Saeed",
            "rating": "1.0",
            "review_text": "Excellent neat and clean rooms. Good management.\nPure and fresh food available.\n24 hours service.\n7 days a week.\nFull 365 days service.\nAir conditioned and none air conditioned rooms are available on very reasonable prices.\nService is good.\nVery nice and Prime location.\nIn night you can view all Rawalpindi from top of roof.\nFeel like home.",
            "date": ""
        },
        {
            "review_id": "Ci9DQUlRQUNvZENodHljRjlvT25FMU0wMDVjVFJGTWpadmFYQkdZakJXYVRoNWFYYxAB",
            "reviewer": "Malik Jan",
            "rating": "No rating",
            "review_text": "Nice hotel best view",
            "date": ""
        },
        {
            "review_id": "Ci9DQUlRQUNvZENodHljRjlvT2tZNFpqZE9Va3BUZDNGWWJ6VnphMkp1VlVobU5XYxAB",
            "reviewer": "Saghir Ali",
            "rating": "No rating",
            "review_text": "Very good",
            "date": ""
        },
        {
            "review_id": "Ci9DQUlRQUNvZENodHljRjlvT2kwMVFrMDNhSFZOYTBWTlgyWmxkMUZVVUVGR04xRRAB",
            "reviewer": "Ghousudin Ahmadi",
            "rating": "No rating",
            "review_text": "Very Nice 💯\nVery good 👍",
            "date": ""
        },
        {
            "review_id": "Ci9DQUlRQUNvZENodHljRjlvT20xRFpHSktTamwzTmpCT1FUbHlRV2g2T0ZscE9VRRAB",
            "reviewer": "Abdulqayoom Lakho",
            "rating": "No rating",
            "review_text": "Unbelievable service and testy food",
            "date": ""
        },
        {
            "review_id": "Ci9DQUlRQUNvZENodHljRjlvT21SWWFTMWZZVXQzT1VsdmMxUkVRMkkxUm1wWU5rRRAB",
            "reviewer": "Shahid Ali Khan",
            "rating": "No rating",
            "review_text": "Nice place and clean atmosphere",
            "date": ""
        },
        {
            "review_id": "Ci9DQUlRQUNvZENodHljRjlvT21GYU9EZFhlblIxTWpKaE16bE9jRWhEYVhCcVJFRRAB",
            "reviewer": "Umar Khan",
            "rating": "No rating",
            "review_text": "Very nice hotel",
            "date": ""
        }
    ]
}